pit/__init__.py
pit/viper/__init__.py
pit/viper/__version__.py
pit/viper/_config.py
pit/viper/_env.py
pit/viper/_io.py
pit/viper/py.typed
pit_viper-1.1.0.dist-info/LICENSE
pit_viper-1.1.0.dist-info/METADATA
pit_viper-1.1.0.dist-info/WHEEL
pit_viper-1.1.0.dist-info/RECORD
