Metadata-Version: 2.1
Name: pit-viper
Version: 1.1.0
Summary: Pit-Viper is a Python package that offers configuration management capabilities like the Viper package in Golang.
Home-page: https://github.com/leoschleier/pit-viper
License: MIT
Keywords: pit-viper
Author: Leo Schleier
Author-email: 43878374+leoschleier@users.noreply.github.com
Requires-Python: >=3.11,<4.0
Classifier: License :: OSI Approved :: MIT License
Classifier: Programming Language :: Python :: 3
Classifier: Programming Language :: Python :: 3.11
Classifier: Programming Language :: Python :: 3.12
Requires-Dist: pyyaml (>=6.0.1,<7.0.0)
